{
  "feature": "test hello world API",
  "epic_id": "EPIC-20251022_124609",
  "phase": "testing",
  "checkpoints": {
    "research": {
      "completed_at": "2025-10-22T12:46:09.298292",
      "result": {
        "patterns": "research/patterns_test hello world API.md",
        "best_practices": "research/best_practices_test hello world API.md",
        "notion_url": "https://notion.so/research-page",
        "epic_id": "EPIC-20251022_124609"
      }
    },
    "planning": {
      "completed_at": "2025-10-22T12:46:10.414798",
      "result": {
        "spec_id": "spec_EPIC-20251022_124609",
        "chroma_collection": "specifications",
        "linear_tasks": [
          "TASK-001: Implement models",
          "TASK-002: Create services",
          "TASK-003: Build API endpoints",
          "TASK-004: Write tests"
        ],
        "notion_updated": true
      }
    },
    "development": {
      "completed_at": "2025-10-22T12:46:12.564289",
      "result": {
        "files_created": [
          "src/features/test hello world API/models.py",
          "src/features/test hello world API/services.py",
          "src/features/test hello world API/api.py",
          "tests/test_test hello world API.py"
        ],
        "supermemory_entries": 5,
        "browser_tests": 3
      }
    },
    "testing": {
      "completed_at": "2025-10-22T12:46:12.572895",
      "result": {
        "unit_tests": {
          "passed": 10,
          "failed": 0
        },
        "integration_tests": {
          "passed": 5,
          "failed": 0
        },
        "browser_tests": {
          "passed": 3,
          "failed": 0
        },
        "coverage": 95.5,
        "all_passed": true
      }
    }
  },
  "outputs": {
    "research": {
      "patterns": "research/patterns_test hello world API.md",
      "best_practices": "research/best_practices_test hello world API.md",
      "notion_url": "https://notion.so/research-page",
      "epic_id": "EPIC-20251022_124609"
    },
    "planning": {
      "spec_id": "spec_EPIC-20251022_124609",
      "chroma_collection": "specifications",
      "linear_tasks": [
        "TASK-001: Implement models",
        "TASK-002: Create services",
        "TASK-003: Build API endpoints",
        "TASK-004: Write tests"
      ],
      "notion_updated": true
    },
    "development": {
      "files_created": [
        "src/features/test hello world API/models.py",
        "src/features/test hello world API/services.py",
        "src/features/test hello world API/api.py",
        "tests/test_test hello world API.py"
      ],
      "supermemory_entries": 5,
      "browser_tests": 3
    },
    "testing": {
      "unit_tests": {
        "passed": 10,
        "failed": 0
      },
      "integration_tests": {
        "passed": 5,
        "failed": 0
      },
      "browser_tests": {
        "passed": 3,
        "failed": 0
      },
      "coverage": 95.5,
      "all_passed": true
    }
  },
  "errors": []
}